nimbuscasino/__init__.py
nimbuscasino/coinflip.py
nimbuscasino/roulette.py
nimbuscasino/rps.py
nimbuscasino/slots.py
nimbuscasino-0.1.2.dist-info/licenses/LICENSE
nimbuscasino-0.1.2.dist-info/METADATA
nimbuscasino-0.1.2.dist-info/WHEEL
nimbuscasino-0.1.2.dist-info/entry_points.txt
nimbuscasino-0.1.2.dist-info/top_level.txt
nimbuscasino-0.1.2.dist-info/RECORD
