Metadata-Version: 2.4
Name: nimbuscasino
Version: 0.1.2
Summary: An example of a package developed with pipenv, built with build using setuptools, uploaded to PyPI using twine, and distributed via pip.
Author-email: Mojin Yuan <my2384@nyu.edu>
License:                     GNU GENERAL PUBLIC LICENSE
Project-URL: Homepage, https://github.com/swe-students-fall2025/3-python-package-team_nimbus
Project-URL: Repository, https://github.com/swe-students-fall2025/3-python-package-team_nimbus.git
Project-URL: Bug Tracker, https://github.com/swe-students-fall2025/3-python-package-team_nimbus/issues
Keywords: python,package,build,minigames
Classifier: Programming Language :: Python :: 3
Classifier: Intended Audience :: Education
Classifier: License :: OSI Approved :: GNU General Public License v3 (GPLv3)
Classifier: Operating System :: OS Independent
Requires-Python: >=3.7
License-File: LICENSE
Provides-Extra: dev
Requires-Dist: pytest; extra == "dev"
Dynamic: license-file
